<?xml version="1.0" encoding="utf-8"?>
<Recent>
  <File>D:\Github\tkEngine2\GameTemplate\tkTools\Effekseer132\Sample\01_Pierre01\MissileBoost.efkproj</File>
  <File>D:\Github\tkEngine2\GameTemplate\tkTools\Effekseer132\Sample\01_Pierre01\Background.efkproj</File>
  <File>D:\Github\tkEngine2\GameTemplate\tkTools\Effekseer132\Sample\01_Pierre01\Flame.efkproj</File>
  <File>D:\Github\tkEngine2\GameTemplate\tkTools\Effekseer132\Sample\01_Pierre01\Atmosphere.efkproj</File>
  <File>D:\Github\tkEngine2\GameTemplate\tkTools\Effekseer132\Sample\01_Pierre01\HolySandstorm.efkproj</File>
  <File>C:\Users\mfami\Desktop\BCR\tkTools\Effekseer132\Sample\00_Basic\Simple_Ring_Shape2.efkproj</File>
  <File>C:\Users\mfami\Desktop\BCR\tkTools\Effekseer132\Sample\00_Basic\Simple_Ring_Shape1.efkproj</File>
  <File>C:\Users\mfami\Desktop\BCR\tkTools\Effekseer132\Sample\01_AndrewFM01\fire.efkproj</File>
  <File>C:\Users\mfami\Desktop\BCR\Game\Assets\effect\Homing_Laser01.efkproj</File>
  <File>C:\Users\mfami\Desktop\effektサンプル\01_Sample\01_Sample\Sample.efkproj</File>
</Recent>